minidump/__amain__.py
minidump/__init__.py
minidump/__main__.py
minidump/_version.py
minidump/aminidumpfile.py
minidump/aminidumpreader.py
minidump/common_structs.py
minidump/constants.py
minidump/directory.py
minidump/exceptions.py
minidump/header.py
minidump/minidumpfile.py
minidump/minidumpreader.py
minidump/minidumpshell.py
minidump/win_datatypes.py
minidump/writer.py
minidump/streams/CommentStreamA.py
minidump/streams/CommentStreamW.py
minidump/streams/ContextStream.py
minidump/streams/ExceptionStream.py
minidump/streams/FunctionTableStream.py
minidump/streams/HandleDataStream.py
minidump/streams/HandleOperationListStream.py
minidump/streams/JavaScriptDataStream.py
minidump/streams/LastReservedStream.py
minidump/streams/Memory64ListStream.py
minidump/streams/MemoryInfoListStream.py
minidump/streams/MemoryListStream.py
minidump/streams/MiscInfoStream.py
minidump/streams/ModuleListStream.py
minidump/streams/ProcessVmCountersStream.py
minidump/streams/SystemInfoStream.py
minidump/streams/SystemMemoryInfoStream.py
minidump/streams/ThreadExListStream.py
minidump/streams/ThreadInfoListStream.py
minidump/streams/ThreadListStream.py
minidump/streams/TokenStream.py
minidump/streams/UnloadedModuleListStream.py
minidump/streams/__init__.py
minidump/utils/__init__.py
minidump/utils/createminidump.py
minidump/utils/privileges.py
minidump/utils/privileges_types.py
minidump/utils/winapi/__init__.py
minidump/utils/winapi/defines.py
minidump/utils/winapi/kernel32.py
minidump/utils/winapi/psapi.py
minidump/utils/winapi/version.py
minidump-0.0.23.dist-info/LICENSE
minidump-0.0.23.dist-info/METADATA
minidump-0.0.23.dist-info/WHEEL
minidump-0.0.23.dist-info/entry_points.txt
minidump-0.0.23.dist-info/top_level.txt
minidump-0.0.23.dist-info/RECORD
